nonebot_plugin_pixiv/__init__.py
nonebot_plugin_pixiv/config.py
nonebot_plugin_pixiv/data_source.py
nonebot_plugin_pixiv-1.1.5.dist-info/METADATA
nonebot_plugin_pixiv-1.1.5.dist-info/WHEEL
nonebot_plugin_pixiv-1.1.5.dist-info/top_level.txt
nonebot_plugin_pixiv-1.1.5.dist-info/RECORD
