Metadata-Version: 2.1
Name: nonebot-plugin-pixiv
Version: 1.1.5
Summary: pixiv.net 查询图片，支持动图和多图
Home-page: https://github.com/anlen123/nonebot_plugin_pixiv
Author: anlen123
Author-email: 1761512493@qq.com
Maintainer: anlen123
Maintainer-email: 1761512493@qq.com
License: UNKNOWN
Platform: all
Requires-Dist: aiohttp
Requires-Dist: nonebot-adapter-onebot (<3.0.0,>=2.0.0-beta.1)
Requires-Dist: nonebot2 (<3.0.0,>=2.0.0-beta.1)
Requires-Dist: opencv-python
